techcable/orderedset/__init__.py
techcable/orderedset/_orderedset.py
techcable/orderedset/_version.py
techcable/orderedset/py.typed
techcable_orderedset-0.1.8.dist-info/METADATA
techcable_orderedset-0.1.8.dist-info/WHEEL
techcable_orderedset-0.1.8.dist-info/licenses/LICENSE-APACHE.txt
techcable_orderedset-0.1.8.dist-info/licenses/LICENSE-MIT.txt
techcable_orderedset-0.1.8.dist-info/RECORD
