Metadata-Version: 2.4
Name: techcable.orderedset
Version: 0.1.8
Summary: A simple and efficient OrderedSet implementation
Project-URL: Source, https://github.com/Techcable/orderedset.py
Author: Techcable
License-Expression: MIT OR Apache-2.0
License-File: LICENSE-APACHE.txt
License-File: LICENSE-MIT.txt
Keywords: ordereddict,orderedset,set
Classifier: Development Status :: 4 - Beta
Classifier: Programming Language :: Python :: 3
Classifier: Topic :: Utilities
Classifier: Typing :: Typed
Requires-Python: >=3.9
Provides-Extra: pydantic
Requires-Dist: pydantic~=2.11; extra == 'pydantic'
Requires-Dist: typing-extensions>=4.12; (python_version <= '3.9') and extra == 'pydantic'
